MANIFEST.in
README.md
setup.py
python3_wrapper_vcx.egg-info/PKG-INFO
python3_wrapper_vcx.egg-info/SOURCES.txt
python3_wrapper_vcx.egg-info/dependency_links.txt
python3_wrapper_vcx.egg-info/top_level.txt
vcx/__init__.py
vcx/cdll.py
vcx/common.py
vcx/error.py
vcx/logging.py
vcx/state.py
vcx/api/__init__.py
vcx/api/connection.py
vcx/api/credential.py
vcx/api/credential_def.py
vcx/api/disclosed_proof.py
vcx/api/issuer_credential.py
vcx/api/proof.py
vcx/api/schema.py
vcx/api/utils.py
vcx/api/vcx_base.py
vcx/api/vcx_init.py
vcx/api/vcx_stateful.py
vcx/api/wallet.py