Metadata-Version: 1.0
Name: python3-wrapper-vcx
Version: 0.2.3
Summary: Python 3 wrapper for libcxs
Home-page: UNKNOWN
Author: Devin Fisher, Ryan Marsh, Mark Hadley, Doug Wightman
Author-email: ryan.marsh@evernym.com
License: UNKNOWN
Platform: UNKNOWN
